continuoussets/__init__.py
continuoussets/convexsets/__init__.py
continuoussets/convexsets/convexset.py
continuoussets/convexsets/interval.py
continuoussets/convexsets/zonotope.py
continuoussets/utils/__init__.py
continuoussets/utils/comparison.py
continuoussets/utils/exceptions.py
continuoussets-0.0.0.dist-info/LICENSE
continuoussets-0.0.0.dist-info/METADATA
continuoussets-0.0.0.dist-info/WHEEL
continuoussets-0.0.0.dist-info/RECORD
