Metadata-Version: 2.1
Name: continuoussets
Version: 0.0.0
Summary: A package for set-based computing.
License: GNU
Keywords: Set-based computing,Interval arithmetic,Zonotopes
Author: Mark Wetzlinger
Author-email: m.wetzlinger@tum.de
Requires-Python: >=3.9,<=3.12
Classifier: License :: Other/Proprietary License
Classifier: Programming Language :: Python :: 3
Classifier: Programming Language :: Python :: 3.9
Classifier: Programming Language :: Python :: 3.10
Classifier: Programming Language :: Python :: 3.11
Classifier: Programming Language :: Python :: 3.12
Requires-Dist: matplotlib (>=3.6.0)
Requires-Dist: numpy (>=1.26.0)
Requires-Dist: scipy (>=1.11.1)
